{"highlights":[{"id":"MDEwOlJlcG9zaXRvcnkyMzY1NTg4NTQ=","title":"cli-config","description":"Helping you setup your CLI experience easily. Some goodies for the ol' terminal.","url":"https://github.com/mrsauravsahu/cli-config","type":1,"createdAt":"2020-01-27T18:12:52Z"},{"id":"MDEwOlJlcG9zaXRvcnkyMTc1NDM3Njc=","title":"mrsauravsahu.github.io","description":"My portfolio website. Tells the world who I am.","url":"https://github.com/mrsauravsahu/mrsauravsahu.github.io","type":1,"createdAt":"2019-10-25T13:48:14Z"},{"id":"MDEwOlJlcG9zaXRvcnkxMTkwMTQyMTg=","title":"gitRemoteToUrl","description":"Converts git's remote url to a valid url to open in the browser.","url":"https://github.com/mrsauravsahu/gitRemoteToUrl","type":1,"createdAt":"2018-01-26T06:22:18Z"},{"id":"MDEwOlJlcG9zaXRvcnk3NDk5MDY2OQ==","title":"TowerOfHanoi","description":"Cross platform Tower of Hanoi game using GLUT for Windows and freeglut for Linux and Mac.","url":"https://github.com/mrsauravsahu/TowerOfHanoi","type":1,"createdAt":"2016-11-28T16:14:03Z"}],"latestBlog":{"id":39,"title":"Hello comments!","description":"Let's allow for some interactions... Enter, comments.","slug":"hello-comments","createdAt":"2020-09-30T11:44:56","file":"content.md","wordCount":391,"approxTimeToRead":"PT1M","images":[],"containerBasePath":"39-hello-comments"}}